mongo_schematic/__init__.py
mongo_schematic/ai.py
mongo_schematic/analyze.py
mongo_schematic/cli.py
mongo_schematic/config.py
mongo_schematic/db.py
mongo_schematic/diff.py
mongo_schematic/docs_gen.py
mongo_schematic/drift.py
mongo_schematic/exceptions.py
mongo_schematic/hooks.py
mongo_schematic/indexes.py
mongo_schematic/migrate.py
mongo_schematic/models.py
mongo_schematic/monitor.py
mongo_schematic/reporting.py
mongo_schematic/schema_io.py
mongo_schematic/seed.py
mongo_schematic/utils.py
mongo_schematic/validate.py
mongo_schematic/codegen/__init__.py
mongo_schematic/codegen/pydantic.py
mongo_schematic/codegen/typescript.py
mongo_schematic-0.1.4.4.dist-info/licenses/LICENSE
mongo_schematic-0.1.4.4.dist-info/METADATA
mongo_schematic-0.1.4.4.dist-info/WHEEL
mongo_schematic-0.1.4.4.dist-info/entry_points.txt
mongo_schematic-0.1.4.4.dist-info/top_level.txt
mongo_schematic-0.1.4.4.dist-info/RECORD
