Metadata-Version: 2.4
Name: mongo-schematic
Version: 0.1.4.4
Summary: MongoSchematic CLI for MongoDB schema analysis, drift detection, and migrations
Author-email: Abdulazeez Abdulazeez Adeshina <abdulazeez@thecodecafe.co>
License: MIT
Classifier: Development Status :: 4 - Beta
Classifier: Intended Audience :: Developers
Classifier: License :: OSI Approved :: MIT License
Classifier: Programming Language :: Python :: 3.10
Classifier: Programming Language :: Python :: 3.11
Classifier: Programming Language :: Python :: 3.12
Classifier: Topic :: Database
Requires-Python: >=3.10
License-File: LICENSE
Requires-Dist: typer[all]>=0.12.0
Requires-Dist: rich>=13.7.0
Requires-Dist: beanie>=1.25.0
Requires-Dist: motor>=3.4.0
Requires-Dist: pymongo>=4.6.1
Requires-Dist: pydantic>=2.6.0
Requires-Dist: pydantic-settings>=2.2.0
Requires-Dist: pyyaml>=6.0.1
Requires-Dist: jsonschema>=4.20.0
Requires-Dist: google-generativeai>=0.3.2
Requires-Dist: python-dotenv>=1.0.1
Requires-Dist: Faker>=24.0.0
Provides-Extra: dev
Requires-Dist: pytest>=8.0.0; extra == "dev"
Requires-Dist: pytest-asyncio>=0.23.0; extra == "dev"
Dynamic: license-file
